{
  "version": "2.6.0",
  "summary": {
    "title": "Threat Model",
    "owner": "gahssi",
    "description": "",
    "id": 0
  },
  "detail": {
    "contributors": [],
    "diagrams": [
      {
        "id": 0,
        "title": "OpenSSL Threat Model",
        "diagramType": "STRIDE",
        "placeholder": "New STRIDE diagram description",
        "thumbnail": "./public/content/images/thumbnail.stride.jpg",
        "version": "2.6.0",
        "cells": [
          {
            "position": {
              "x": 210,
              "y": 190
            },
            "size": {
              "width": 112.5,
              "height": 60
            },
            "attrs": {
              "text": {
                "text": "User"
              },
              "body": {
                "stroke": "#333333",
                "strokeWidth": 1.5,
                "strokeDasharray": null
              }
            },
            "visible": true,
            "shape": "actor",
            "ports": {
              "groups": {
                "top": {
                  "position": "top",
                  "attrs": {
                    "circle": {
                      "r": 4,
                      "magnet": true,
                      "stroke": "#5F95FF",
                      "strokeWidth": 1,
                      "fill": "#fff",
                      "style": {
                        "visibility": "hidden"
                      }
                    }
                  }
                },
                "right": {
                  "position": "right",
                  "attrs": {
                    "circle": {
                      "r": 4,
                      "magnet": true,
                      "stroke": "#5F95FF",
                      "strokeWidth": 1,
                      "fill": "#fff",
                      "style": {
                        "visibility": "hidden"
                      }
                    }
                  }
                },
                "bottom": {
                  "position": "bottom",
                  "attrs": {
                    "circle": {
                      "r": 4,
                      "magnet": true,
                      "stroke": "#5F95FF",
                      "strokeWidth": 1,
                      "fill": "#fff",
                      "style": {
                        "visibility": "hidden"
                      }
                    }
                  }
                },
                "left": {
                  "position": "left",
                  "attrs": {
                    "circle": {
                      "r": 4,
                      "magnet": true,
                      "stroke": "#5F95FF",
                      "strokeWidth": 1,
                      "fill": "#fff",
                      "style": {
                        "visibility": "hidden"
                      }
                    }
                  }
                }
              },
              "items": [
                {
                  "group": "top",
                  "id": "12ac2e4c-f67f-4f5c-8961-4088365a1280"
                },
                {
                  "group": "right",
                  "id": "bdf7b2f1-02f3-4b91-a2fc-e2ca403d56d9"
                },
                {
                  "group": "bottom",
                  "id": "0ba20bd1-c86f-4000-bb0c-c5517c608b86"
                },
                {
                  "group": "left",
                  "id": "6a9bd826-ee56-4567-bcf2-e5090d117955"
                }
              ]
            },
            "id": "f26c90e7-0bbd-49b5-a937-4b175a2437d5",
            "zIndex": 1,
            "data": {
              "type": "tm.Actor",
              "name": "User",
              "description": "",
              "isTrustBoundary": false,
              "outOfScope": false,
              "reasonOutOfScope": "",
              "hasOpenThreats": false,
              "providesAuthentication": false,
              "threats": []
            }
          },
          {
            "position": {
              "x": 122.5,
              "y": 707
            },
            "size": {
              "width": 120,
              "height": 60
            },
            "attrs": {
              "text": {
                "text": "RAM\n(KeyGen Context)"
              },
              "topLine": {
                "strokeWidth": 1.5,
                "strokeDasharray": null
              },
              "bottomLine": {
                "strokeWidth": 1.5,
                "strokeDasharray": null
              }
            },
            "visible": true,
            "shape": "store",
            "ports": {
              "groups": {
                "top": {
                  "position": "top",
                  "attrs": {
                    "circle": {
                      "r": 4,
                      "magnet": true,
                      "stroke": "#5F95FF",
                      "strokeWidth": 1,
                      "fill": "#fff",
                      "style": {
                        "visibility": "hidden"
                      }
                    }
                  }
                },
                "right": {
                  "position": "right",
                  "attrs": {
                    "circle": {
                      "r": 4,
                      "magnet": true,
                      "stroke": "#5F95FF",
                      "strokeWidth": 1,
                      "fill": "#fff",
                      "style": {
                        "visibility": "hidden"
                      }
                    }
                  }
                },
                "bottom": {
                  "position": "bottom",
                  "attrs": {
                    "circle": {
                      "r": 4,
                      "magnet": true,
                      "stroke": "#5F95FF",
                      "strokeWidth": 1,
                      "fill": "#fff",
                      "style": {
                        "visibility": "hidden"
                      }
                    }
                  }
                },
                "left": {
                  "position": "left",
                  "attrs": {
                    "circle": {
                      "r": 4,
                      "magnet": true,
                      "stroke": "#5F95FF",
                      "strokeWidth": 1,
                      "fill": "#fff",
                      "style": {
                        "visibility": "hidden"
                      }
                    }
                  }
                }
              },
              "items": [
                {
                  "group": "top",
                  "id": "d9979f19-98c6-4100-bba5-9ac39ec7388e"
                },
                {
                  "group": "right",
                  "id": "517077ba-683e-4b73-8068-9384e4ba4371"
                },
                {
                  "group": "bottom",
                  "id": "ef949e23-28fa-4a78-81fa-e77b41cd8c08"
                },
                {
                  "group": "left",
                  "id": "952aae6b-4a2f-45b6-8ac1-433d35d7829e"
                }
              ]
            },
            "id": "87162051-ee08-4a5d-9dba-38cbe937cb42",
            "zIndex": 2,
            "data": {
              "type": "tm.Store",
              "name": "RAM\n(KeyGen Context)",
              "description": "",
              "outOfScope": false,
              "isTrustBoundary": false,
              "reasonOutOfScope": "",
              "hasOpenThreats": false,
              "isALog": false,
              "isEncrypted": false,
              "isSigned": false,
              "storesCredentials": false,
              "storesInventory": false,
              "threats": []
            }
          },
          {
            "position": {
              "x": 990,
              "y": 340
            },
            "size": {
              "width": 112.5,
              "height": 60
            },
            "attrs": {
              "text": {
                "text": "System\nAdministrator"
              },
              "body": {
                "stroke": "#333333",
                "strokeWidth": 1.5,
                "strokeDasharray": null
              }
            },
            "visible": true,
            "shape": "actor",
            "ports": {
              "groups": {
                "top": {
                  "position": "top",
                  "attrs": {
                    "circle": {
                      "r": 4,
                      "magnet": true,
                      "stroke": "#5F95FF",
                      "strokeWidth": 1,
                      "fill": "#fff",
                      "style": {
                        "visibility": "hidden"
                      }
                    }
                  }
                },
                "right": {
                  "position": "right",
                  "attrs": {
                    "circle": {
                      "r": 4,
                      "magnet": true,
                      "stroke": "#5F95FF",
                      "strokeWidth": 1,
                      "fill": "#fff",
                      "style": {
                        "visibility": "hidden"
                      }
                    }
                  }
                },
                "bottom": {
                  "position": "bottom",
                  "attrs": {
                    "circle": {
                      "r": 4,
                      "magnet": true,
                      "stroke": "#5F95FF",
                      "strokeWidth": 1,
                      "fill": "#fff",
                      "style": {
                        "visibility": "hidden"
                      }
                    }
                  }
                },
                "left": {
                  "position": "left",
                  "attrs": {
                    "circle": {
                      "r": 4,
                      "magnet": true,
                      "stroke": "#5F95FF",
                      "strokeWidth": 1,
                      "fill": "#fff",
                      "style": {
                        "visibility": "hidden"
                      }
                    }
                  }
                }
              },
              "items": [
                {
                  "group": "top",
                  "id": "12ac2e4c-f67f-4f5c-8961-4088365a1280"
                },
                {
                  "group": "right",
                  "id": "bdf7b2f1-02f3-4b91-a2fc-e2ca403d56d9"
                },
                {
                  "group": "bottom",
                  "id": "0ba20bd1-c86f-4000-bb0c-c5517c608b86"
                },
                {
                  "group": "left",
                  "id": "6a9bd826-ee56-4567-bcf2-e5090d117955"
                }
              ]
            },
            "id": "ab78ca18-9562-478b-8e04-573042ee0a99",
            "zIndex": 3,
            "data": {
              "type": "tm.Actor",
              "name": "System\nAdministrator",
              "description": "",
              "isTrustBoundary": false,
              "outOfScope": false,
              "reasonOutOfScope": "",
              "hasOpenThreats": false,
              "providesAuthentication": false,
              "threats": []
            }
          },
          {
            "position": {
              "x": 440,
              "y": 330
            },
            "size": {
              "width": 90,
              "height": 90
            },
            "attrs": {
              "text": {
                "text": "Host \nApplication"
              },
              "body": {
                "stroke": "#333333",
                "strokeWidth": 1.5,
                "strokeDasharray": null
              }
            },
            "visible": true,
            "shape": "process",
            "ports": {
              "groups": {
                "top": {
                  "position": "top",
                  "attrs": {
                    "circle": {
                      "r": 4,
                      "magnet": true,
                      "stroke": "#5F95FF",
                      "strokeWidth": 1,
                      "fill": "#fff",
                      "style": {
                        "visibility": "hidden"
                      }
                    }
                  }
                },
                "right": {
                  "position": "right",
                  "attrs": {
                    "circle": {
                      "r": 4,
                      "magnet": true,
                      "stroke": "#5F95FF",
                      "strokeWidth": 1,
                      "fill": "#fff",
                      "style": {
                        "visibility": "hidden"
                      }
                    }
                  }
                },
                "bottom": {
                  "position": "bottom",
                  "attrs": {
                    "circle": {
                      "r": 4,
                      "magnet": true,
                      "stroke": "#5F95FF",
                      "strokeWidth": 1,
                      "fill": "#fff",
                      "style": {
                        "visibility": "hidden"
                      }
                    }
                  }
                },
                "left": {
                  "position": "left",
                  "attrs": {
                    "circle": {
                      "r": 4,
                      "magnet": true,
                      "stroke": "#5F95FF",
                      "strokeWidth": 1,
                      "fill": "#fff",
                      "style": {
                        "visibility": "hidden"
                      }
                    }
                  }
                }
              },
              "items": [
                {
                  "group": "top",
                  "id": "ebebf265-31ec-42bc-929a-87edb05a3e37"
                },
                {
                  "group": "right",
                  "id": "87fc6407-5386-409f-bb54-2794cdfe9c04"
                },
                {
                  "group": "bottom",
                  "id": "e8e18413-07a1-49d5-843c-40626cc923df"
                },
                {
                  "group": "left",
                  "id": "a63693af-711d-4d13-9f3a-15deeccaaf0c"
                }
              ]
            },
            "id": "c5d1cc71-52c4-4428-b805-ce9fd0930bbc",
            "zIndex": 4,
            "data": {
              "type": "tm.Process",
              "name": "Host \nApplication",
              "description": "",
              "outOfScope": false,
              "isTrustBoundary": false,
              "reasonOutOfScope": "",
              "hasOpenThreats": false,
              "handlesCardPayment": false,
              "handlesGoodsOrServices": false,
              "isWebApplication": false,
              "privilegeLevel": "",
              "threats": []
            }
          },
          {
            "position": {
              "x": 440,
              "y": 530
            },
            "size": {
              "width": 90,
              "height": 90
            },
            "attrs": {
              "text": {
                "text": "libssl"
              },
              "body": {
                "stroke": "#333333",
                "strokeWidth": 1.5,
                "strokeDasharray": null
              }
            },
            "visible": true,
            "shape": "process",
            "ports": {
              "groups": {
                "top": {
                  "position": "top",
                  "attrs": {
                    "circle": {
                      "r": 4,
                      "magnet": true,
                      "stroke": "#5F95FF",
                      "strokeWidth": 1,
                      "fill": "#fff",
                      "style": {
                        "visibility": "hidden"
                      }
                    }
                  }
                },
                "right": {
                  "position": "right",
                  "attrs": {
                    "circle": {
                      "r": 4,
                      "magnet": true,
                      "stroke": "#5F95FF",
                      "strokeWidth": 1,
                      "fill": "#fff",
                      "style": {
                        "visibility": "hidden"
                      }
                    }
                  }
                },
                "bottom": {
                  "position": "bottom",
                  "attrs": {
                    "circle": {
                      "r": 4,
                      "magnet": true,
                      "stroke": "#5F95FF",
                      "strokeWidth": 1,
                      "fill": "#fff",
                      "style": {
                        "visibility": "hidden"
                      }
                    }
                  }
                },
                "left": {
                  "position": "left",
                  "attrs": {
                    "circle": {
                      "r": 4,
                      "magnet": true,
                      "stroke": "#5F95FF",
                      "strokeWidth": 1,
                      "fill": "#fff",
                      "style": {
                        "visibility": "hidden"
                      }
                    }
                  }
                }
              },
              "items": [
                {
                  "group": "top",
                  "id": "ebebf265-31ec-42bc-929a-87edb05a3e37"
                },
                {
                  "group": "right",
                  "id": "87fc6407-5386-409f-bb54-2794cdfe9c04"
                },
                {
                  "group": "bottom",
                  "id": "e8e18413-07a1-49d5-843c-40626cc923df"
                },
                {
                  "group": "left",
                  "id": "a63693af-711d-4d13-9f3a-15deeccaaf0c"
                }
              ]
            },
            "id": "dfdaa0b0-73ac-43d6-a785-9dec3d71ac11",
            "data": {
              "type": "tm.Process",
              "name": "libssl",
              "description": "",
              "outOfScope": false,
              "isTrustBoundary": false,
              "reasonOutOfScope": "",
              "hasOpenThreats": false,
              "handlesCardPayment": false,
              "handlesGoodsOrServices": false,
              "isWebApplication": false,
              "privilegeLevel": "",
              "threats": []
            },
            "zIndex": 5
          },
          {
            "position": {
              "x": 440,
              "y": 692
            },
            "size": {
              "width": 90,
              "height": 90
            },
            "attrs": {
              "text": {
                "text": "libcrypto"
              },
              "body": {
                "stroke": "#333333",
                "strokeWidth": 1.5,
                "strokeDasharray": null
              }
            },
            "visible": true,
            "shape": "process",
            "ports": {
              "groups": {
                "top": {
                  "position": "top",
                  "attrs": {
                    "circle": {
                      "r": 4,
                      "magnet": true,
                      "stroke": "#5F95FF",
                      "strokeWidth": 1,
                      "fill": "#fff",
                      "style": {
                        "visibility": "hidden"
                      }
                    }
                  }
                },
                "right": {
                  "position": "right",
                  "attrs": {
                    "circle": {
                      "r": 4,
                      "magnet": true,
                      "stroke": "#5F95FF",
                      "strokeWidth": 1,
                      "fill": "#fff",
                      "style": {
                        "visibility": "hidden"
                      }
                    }
                  }
                },
                "bottom": {
                  "position": "bottom",
                  "attrs": {
                    "circle": {
                      "r": 4,
                      "magnet": true,
                      "stroke": "#5F95FF",
                      "strokeWidth": 1,
                      "fill": "#fff",
                      "style": {
                        "visibility": "hidden"
                      }
                    }
                  }
                },
                "left": {
                  "position": "left",
                  "attrs": {
                    "circle": {
                      "r": 4,
                      "magnet": true,
                      "stroke": "#5F95FF",
                      "strokeWidth": 1,
                      "fill": "#fff",
                      "style": {
                        "visibility": "hidden"
                      }
                    }
                  }
                }
              },
              "items": [
                {
                  "group": "top",
                  "id": "ebebf265-31ec-42bc-929a-87edb05a3e37"
                },
                {
                  "group": "right",
                  "id": "87fc6407-5386-409f-bb54-2794cdfe9c04"
                },
                {
                  "group": "bottom",
                  "id": "e8e18413-07a1-49d5-843c-40626cc923df"
                },
                {
                  "group": "left",
                  "id": "a63693af-711d-4d13-9f3a-15deeccaaf0c"
                }
              ]
            },
            "id": "4adb88b7-d294-4818-9fda-e5c56105881d",
            "data": {
              "type": "tm.Process",
              "name": "libcrypto",
              "description": "",
              "outOfScope": false,
              "isTrustBoundary": false,
              "reasonOutOfScope": "",
              "hasOpenThreats": false,
              "handlesCardPayment": false,
              "handlesGoodsOrServices": false,
              "isWebApplication": false,
              "privilegeLevel": "",
              "threats": []
            },
            "zIndex": 6
          },
          {
            "position": {
              "x": 710,
              "y": 820
            },
            "size": {
              "width": 120,
              "height": 60
            },
            "attrs": {
              "text": {
                "text": "Trust Store"
              },
              "topLine": {
                "strokeWidth": 1.5,
                "strokeDasharray": null
              },
              "bottomLine": {
                "strokeWidth": 1.5,
                "strokeDasharray": null
              }
            },
            "visible": true,
            "shape": "store",
            "ports": {
              "groups": {
                "top": {
                  "position": "top",
                  "attrs": {
                    "circle": {
                      "r": 4,
                      "magnet": true,
                      "stroke": "#5F95FF",
                      "strokeWidth": 1,
                      "fill": "#fff",
                      "style": {
                        "visibility": "hidden"
                      }
                    }
                  }
                },
                "right": {
                  "position": "right",
                  "attrs": {
                    "circle": {
                      "r": 4,
                      "magnet": true,
                      "stroke": "#5F95FF",
                      "strokeWidth": 1,
                      "fill": "#fff",
                      "style": {
                        "visibility": "hidden"
                      }
                    }
                  }
                },
                "bottom": {
                  "position": "bottom",
                  "attrs": {
                    "circle": {
                      "r": 4,
                      "magnet": true,
                      "stroke": "#5F95FF",
                      "strokeWidth": 1,
                      "fill": "#fff",
                      "style": {
                        "visibility": "hidden"
                      }
                    }
                  }
                },
                "left": {
                  "position": "left",
                  "attrs": {
                    "circle": {
                      "r": 4,
                      "magnet": true,
                      "stroke": "#5F95FF",
                      "strokeWidth": 1,
                      "fill": "#fff",
                      "style": {
                        "visibility": "hidden"
                      }
                    }
                  }
                }
              },
              "items": [
                {
                  "group": "top",
                  "id": "d9979f19-98c6-4100-bba5-9ac39ec7388e"
                },
                {
                  "group": "right",
                  "id": "517077ba-683e-4b73-8068-9384e4ba4371"
                },
                {
                  "group": "bottom",
                  "id": "ef949e23-28fa-4a78-81fa-e77b41cd8c08"
                },
                {
                  "group": "left",
                  "id": "952aae6b-4a2f-45b6-8ac1-433d35d7829e"
                }
              ]
            },
            "id": "9ad2fa4d-f9d4-4e85-8650-b5326bf7ffac",
            "zIndex": 7,
            "data": {
              "type": "tm.Store",
              "name": "Trust Store",
              "description": "",
              "outOfScope": false,
              "isTrustBoundary": false,
              "reasonOutOfScope": "",
              "hasOpenThreats": false,
              "isALog": false,
              "isEncrypted": false,
              "isSigned": false,
              "storesCredentials": false,
              "storesInventory": false,
              "threats": []
            }
          },
          {
            "position": {
              "x": 960,
              "y": 740
            },
            "size": {
              "width": 120,
              "height": 60
            },
            "attrs": {
              "text": {
                "text": "Private Keys"
              },
              "topLine": {
                "strokeWidth": 1.5,
                "strokeDasharray": null
              },
              "bottomLine": {
                "strokeWidth": 1.5,
                "strokeDasharray": null
              }
            },
            "visible": true,
            "shape": "store",
            "ports": {
              "groups": {
                "top": {
                  "position": "top",
                  "attrs": {
                    "circle": {
                      "r": 4,
                      "magnet": true,
                      "stroke": "#5F95FF",
                      "strokeWidth": 1,
                      "fill": "#fff",
                      "style": {
                        "visibility": "hidden"
                      }
                    }
                  }
                },
                "right": {
                  "position": "right",
                  "attrs": {
                    "circle": {
                      "r": 4,
                      "magnet": true,
                      "stroke": "#5F95FF",
                      "strokeWidth": 1,
                      "fill": "#fff",
                      "style": {
                        "visibility": "hidden"
                      }
                    }
                  }
                },
                "bottom": {
                  "position": "bottom",
                  "attrs": {
                    "circle": {
                      "r": 4,
                      "magnet": true,
                      "stroke": "#5F95FF",
                      "strokeWidth": 1,
                      "fill": "#fff",
                      "style": {
                        "visibility": "hidden"
                      }
                    }
                  }
                },
                "left": {
                  "position": "left",
                  "attrs": {
                    "circle": {
                      "r": 4,
                      "magnet": true,
                      "stroke": "#5F95FF",
                      "strokeWidth": 1,
                      "fill": "#fff",
                      "style": {
                        "visibility": "hidden"
                      }
                    }
                  }
                }
              },
              "items": [
                {
                  "group": "top",
                  "id": "d9979f19-98c6-4100-bba5-9ac39ec7388e"
                },
                {
                  "group": "right",
                  "id": "517077ba-683e-4b73-8068-9384e4ba4371"
                },
                {
                  "group": "bottom",
                  "id": "ef949e23-28fa-4a78-81fa-e77b41cd8c08"
                },
                {
                  "group": "left",
                  "id": "952aae6b-4a2f-45b6-8ac1-433d35d7829e"
                }
              ]
            },
            "id": "271a4a3f-223c-4505-b126-8e746c4bd582",
            "zIndex": 8,
            "data": {
              "type": "tm.Store",
              "name": "Private Keys",
              "description": "",
              "outOfScope": false,
              "isTrustBoundary": false,
              "reasonOutOfScope": "",
              "hasOpenThreats": false,
              "isALog": false,
              "isEncrypted": false,
              "isSigned": false,
              "storesCredentials": false,
              "storesInventory": false,
              "threats": []
            }
          },
          {
            "position": {
              "x": 797,
              "y": 560
            },
            "size": {
              "width": 120,
              "height": 60
            },
            "attrs": {
              "text": {
                "text": "openssl.conf"
              },
              "topLine": {
                "strokeWidth": 1.5,
                "strokeDasharray": null
              },
              "bottomLine": {
                "strokeWidth": 1.5,
                "strokeDasharray": null
              }
            },
            "visible": true,
            "shape": "store",
            "ports": {
              "groups": {
                "top": {
                  "position": "top",
                  "attrs": {
                    "circle": {
                      "r": 4,
                      "magnet": true,
                      "stroke": "#5F95FF",
                      "strokeWidth": 1,
                      "fill": "#fff",
                      "style": {
                        "visibility": "hidden"
                      }
                    }
                  }
                },
                "right": {
                  "position": "right",
                  "attrs": {
                    "circle": {
                      "r": 4,
                      "magnet": true,
                      "stroke": "#5F95FF",
                      "strokeWidth": 1,
                      "fill": "#fff",
                      "style": {
                        "visibility": "hidden"
                      }
                    }
                  }
                },
                "bottom": {
                  "position": "bottom",
                  "attrs": {
                    "circle": {
                      "r": 4,
                      "magnet": true,
                      "stroke": "#5F95FF",
                      "strokeWidth": 1,
                      "fill": "#fff",
                      "style": {
                        "visibility": "hidden"
                      }
                    }
                  }
                },
                "left": {
                  "position": "left",
                  "attrs": {
                    "circle": {
                      "r": 4,
                      "magnet": true,
                      "stroke": "#5F95FF",
                      "strokeWidth": 1,
                      "fill": "#fff",
                      "style": {
                        "visibility": "hidden"
                      }
                    }
                  }
                }
              },
              "items": [
                {
                  "group": "top",
                  "id": "d9979f19-98c6-4100-bba5-9ac39ec7388e"
                },
                {
                  "group": "right",
                  "id": "517077ba-683e-4b73-8068-9384e4ba4371"
                },
                {
                  "group": "bottom",
                  "id": "ef949e23-28fa-4a78-81fa-e77b41cd8c08"
                },
                {
                  "group": "left",
                  "id": "952aae6b-4a2f-45b6-8ac1-433d35d7829e"
                }
              ]
            },
            "id": "1d4226b8-80b1-4db5-aedf-04f25d71c9d3",
            "zIndex": 9,
            "data": {
              "type": "tm.Store",
              "name": "openssl.conf",
              "description": "",
              "outOfScope": false,
              "isTrustBoundary": false,
              "reasonOutOfScope": "",
              "hasOpenThreats": false,
              "isALog": false,
              "isEncrypted": false,
              "isSigned": false,
              "storesCredentials": false,
              "storesInventory": false,
              "threats": []
            }
          }
        ]
      }
    ],
    "diagramTop": 1,
    "reviewer": "",
    "threatTop": 0
  }
}